packageKinjal/__init__.py
packageKinjal/topsis.py
Topsis_Kinjal_102003532-1.4.0.dist-info/METADATA
Topsis_Kinjal_102003532-1.4.0.dist-info/WHEEL
Topsis_Kinjal_102003532-1.4.0.dist-info/top_level.txt
Topsis_Kinjal_102003532-1.4.0.dist-info/RECORD
