Metadata-Version: 2.1
Name: Topsis-Kinjal-102003532
Version: 1.4.0
Summary: It evaluates alternatives based on multiple criteria using TOPSIS method
Author: Kinjal Goyal
Author-email: <kgoyal1_be20@thapar.edu>
Classifier: Programming Language :: Python :: 3
Classifier: Operating System :: Unix
Classifier: Operating System :: MacOS :: MacOS X
Classifier: Operating System :: Microsoft :: Windows
